pytest_hammertime.py
pytest_hammertime-1.1.1.dist-info/METADATA
pytest_hammertime-1.1.1.dist-info/RECORD
pytest_hammertime-1.1.1.dist-info/WHEEL
pytest_hammertime-1.1.1.dist-info/entry_points.txt
pytest_hammertime-1.1.1.dist-info/top_level.txt
