Metadata-Version: 2.1
Name: pytest-hammertime
Version: 1.1.1
Summary: Display "🔨 " instead of "." for passed pytest tests.
Home-page: https://github.com/zhammer/pytest-hammertime
Author: Zach Hammer
Author-email: zach.the.hammer@gmail.com
License: MIT License
Platform: UNKNOWN
Requires-Dist: pytest
